<?xml version="1.0" encoding="UTF-8" ?>
<Module>
  <ModulePrefs title="Main Menu" />
  <Content type="html">
    <![CDATA[
      <center><font color="#000000"><b><font size="4">- MAIN MENU -</font></b></font></center><script type="text/javascript" src="http://fjamstudios.googlecode.com/svn/trunk/wiget/stmenu.js"></script>
<script type="text/javascript">
<!--
stm_bm(["menu050b",900,"http://fjamstudios.googlecode.com/svn/trunk/wiget","blank.gif",0,"","",1,0,250,0,1000,1,0,0,"","",0,0,1,2,"default","hand","",1,25],this);
stm_bp("p0",[0,4,0,0,0,3,5,7,100,"",-2,"",-2,50,0,0,"#999999","transparent","",3,0,0,"#000000"]);
stm_ai("p0i0",[0,"HOME","","",-1,-1,0,"https://sites.google.com/site/fjatestsite/","_top","","Starting point for navigating F-Jam","","",5,5,0,"","",0,0,0,1,1,"#66CCCC",0,"#66CCCC",0,"","",3,1,0,0,"#FFFFF7","#000000","#FF3300","#000000","bold 9pt Arial","bold 9pt Arial",0,0,"","","","",0,0,0]);
stm_aix("p0i1","p0i0",[0,"Members","","",-1,-1,0,"","_self","","","","",5,5,0,"arrow_r.gif","arrow_r.gif",7,7,0,1,1,"#66CCCC",0,"#66CCCC",0,"","",3,1,0,0,"#FFFFF7","#000000","#000000","#FF3300"]);
stm_bpx("p1","p0",[1,4,0,0,0,3,5,0]);
stm_aix("p1i0","p0i1",[0,"A-F","","",-1,-1,0,"javascript:window.open(\"http://sites.google.com/site/fjamages/a-f\",\"_blank\",\"width=400,height=600,status=no,scrollbars=yes,\");void(0);void(0);void(0)","_self","","Open member avatar/profile pages above based on their name (last name if more than one).","","",5,5,0,"","",0,0,0,0,0]);
stm_aix("p1i1","p1i0",[0,"G-L","","",-1,-1,0,"javascript:window.open(\"http://sites.google.com/site/fjamages/g-l\",\"_blank\",\"width=400,height=600,status=no,scrollbars=yes,\");void(0);void(0);void(0)"]);
stm_aix("p1i2","p1i0",[0,"M-R","","",-1,-1,0,"javascript:window.open(\"http://sites.google.com/site/fjamages/m-r\",\"_blank\",\"width=400,height=600,status=no,scrollbars=yes,\");void(0);void(0);void(0)"]);
stm_aix("p1i3","p1i0",[0,"S-Z","","",-1,-1,0,"javascript:window.open(\"http://sites.google.com/site/fjamages/s-z\",\"_blank\",\"width=400,height=600,status=no,scrollbars=yes,\");void(0);void(0);void(0)"]);
stm_ep();
stm_aix("p0i2","p0i1",[0,"Talent","","",-1,-1,0,"https://www.facebook.com/groups/fjamstudios/#!/groups/fjamstudios/doc/251077994923371/"]);
stm_bpx("p2","p1",[]);
stm_aix("p2i0","p1i0",[0,"Post your talent profile","","",-1,-1,0,"https://sites.google.com/site/fjampages/submit-talent-profile","_blank","","Submit your talent profile. It will be posted to the forum, as well as in the talent groups."]);
stm_aix("p2i1","p1i0",[0,"Talent Listing","","",-1,-1,0,"https://sites.google.com/site/fjatestsite/talent-profiles","_blank","","When a member joins they post a talent profile. Here they are."]);
stm_aix("p2i2","p1i0",[0,"Bassist - Listed/Wanted","","",-1,-1,0,"https://www.facebook.com/home.php#!/groups/fjamstudios/doc/249276511770186/","_blank","","Add your name and profile link to the list (edit it in), and save it, and then LIKE the document and you\'ll get notified via email when someothing is posted wanting this talent."]);
stm_aix("p2i3","p2i2",[0,"Composers - Listed/Wanted","","",-1,-1,0,"https://www.facebook.com/groups/fjamstudios/doc/260928450604992/"]);
stm_aix("p2i4","p2i2",[0,"Drummers - Listed/Wanted","","",-1,-1,0,"https://www.facebook.com/groups/fjamstudios/#!/groups/fjamstudios/doc/251078834923287/"]);
stm_aix("p2i5","p2i2",[0,"Guitarists - Listed/Wanted","","",-1,-1,0,"https://www.facebook.com/home.php#!/groups/fjamstudios/doc/249281188436385/"]);
stm_aix("p2i6","p2i2",[0,"Keyboardists - Listed/Wanted","","",-1,-1,0,"https://www.facebook.com/groups/fjamstudios/#!/groups/fjamstudios/doc/251080824923088/"]);
stm_aix("p2i7","p2i2",[0,"Lyricists - Listed/Wanted","","",-1,-1,0,"https://www.facebook.com/groups/fjamstudios/#!/groups/fjamstudios/doc/251077994923371/"]);
stm_aix("p2i8","p2i2",[0,"Mix/Master Engineer - Listed/Wanted","","",-1,-1,0,"https://www.facebook.com/groups/fjamstudios/#!/groups/fjamstudios/doc/255704151127422/"]);
stm_aix("p2i9","p2i2",[0,"Producers - Listed/Wanted","","",-1,-1,0,"https://www.facebook.com/groups/fjamstudios/#!/groups/fjamstudios/doc/251079774923193/"]);
stm_aix("p2i10","p2i2",[0,"Video Editor","","",-1,-1,0,"https://www.facebook.com/groups/fjamstudios/#!/groups/fjamstudios/doc/251864468178057/"]);
stm_aix("p2i11","p2i2",[0,"Vocalists - Listed/Wanted","","",-1,-1,0,"https://www.facebook.com/home.php#!/groups/fjamstudios/doc/249799195051251/"]);
stm_ep();
stm_aix("p0i3","p0i1",[0,"Start A New Project","","",-1,-1,0,"https://sites.google.com/site/fjatestsite/system/app/pages/createPage?source=/home","_top","","Post A New Collaboration Project","","",5,5,0,"","",0,0]);
stm_aix("p0i4","p0i0",[0,"HELP","","",-1,-1,0,"","_top","","","","",5,5,0,"arrow_r.gif","arrow_r.gif",7,7,0,1,1,"#66CCCC",0,"#66CCCC",0,"","",3,1,0,0,"#FFFFF7","#000000","#FF3300","#333333"]);
stm_bpx("p3","p1",[]);
stm_aix("p3i0","p1i0",[0,"Help Page","","",-1,-1,0,"https://sites.google.com/site/fjatestsite/help","_blank","","Show Help Topics"]);
stm_aix("p3i1","p1i0",[0,"Contact Admin","","",-1,-1,0,"javascript:window.open(\"http://www.tfaforms.com/188611\",\"_blank\",\"width=425,height=700,status=yes,scrollbars=no,\");void(0)","_blank","","Send a message"]);
stm_ep();
stm_aix("p0i5","p0i1",[0,"Lyrics"]);
stm_bpx("p4","p1",[]);
stm_aix("p4i0","p1i0",[0,"Open Lyrics Archive","","",-1,-1,0,"https://sites.google.com/site/fjatestsite/home/lyrics","_top","","Lyric Collection To Browse"]);
stm_ep();
stm_aix("p0i6","p0i1",[0,"Finished Tracks"]);
stm_bpx("p5","p0",[1,4]);
stm_aix("p5i0","p1i0",[0,"F-Jam Radio","","",-1,-1,0,"javascript:window.open(\"https://sites.google.com/site/fjampages/f-jam-radio\",\"_blank\",\"width=425,height=500,status=yes,scrollbars=no,\");void(0)","_self","","Just a small sampling of some of the finished tracks produced here at F-Jam Studios"]);
stm_aix("p5i1","p1i0",[0,"Jukebox","","",-1,-1,0,"https://sites.google.com/site/fjatestsite/finished-tracks-jukebox","_top","","Each song with credits, and lyrics, sorted by genre"]);
stm_aix("p5i2","p1i0",[0,"Favorites","","",-1,-1,0,"https://sites.google.com/site/fjatestsite/favorites","_top","","These are some of our favorite tunes done by artists we know."]);
stm_aix("p5i3","p1i0",[0,"Online Bands","","",-1,-1,0,"","_self","","","","",5,5,0,"arrow_r.gif","arrow_r.gif",7,7]);
stm_bpx("p6","p1",[1,2]);
stm_aix("p6i0","p1i0",[0,"Avalanche (Rock Opera)","","",-1,-1,0,"https://sites.google.com/site/fjatestsite/rock-opera-project","_top","","Yves baar production"]);
stm_aix("p6i1","p1i0",[0,"FLY","","",-1,-1,0,"https://sites.google.com/site/fjatestsite/official-fly-band-page","_top","","Freddy, Laura, and Yves are FLY!"]);
stm_aix("p6i2","p1i0",[0,"Curtain Call","","",-1,-1,0,"https://sites.google.com/site/fjatestsite/official-curtain-call-page","_blank","","Nacho, Mike, and Freddy"]);
stm_ep();
stm_aix("p5i4","p5i3",[0,"Charity Benefits","","",-1,-1,0,"","_blank"]);
stm_bpx("p7","p6",[]);
stm_aix("p7i0","p1i0",[0,"Abe Aid","","",-1,-1,0,"https://sites.google.com/site/abeaid2012/home","_blank","","Live shows and compilation cd to benefit disabled children in the name of Abe Bernard"]);
stm_ep();
stm_ep();
stm_aix("p0i7","p0i1",[0,"Extras"]);
stm_bpx("p8","p1",[]);
stm_aix("p8i0","p1i0",[0,"General Discussions","","",-1,-1,0,"https://sites.google.com/site/fjatestsite/discussions","_top","","This area is for ANY discussions that you\'d like to start, or talk about."]);
stm_aix("p8i1","p1i0",[0,"Add Smilies/Graphics","","",-1,-1,0,"javascript:window.open(\"https://sites.google.com/site/fjampages/add-graphics\",\"_blank\",\"width=275,height=400,status=yes,scrollbars=no,\");void(0);void(0)","_self","","Lets you use smilies and other graphics in your posts"]);
stm_aix("p8i2","p1i0",[0,"Chat","","",-1,-1,0,"javascript:window.open(\"http://talkgadget.google.com/talkgadget/popout\",\"_blank\",\"width=200,height=600,status=yes,scrollbars=yes,\");void(0)","_self","","Google Talk App"]);
stm_aix("p8i3","p1i0",[0,"Avatars","","",-1,-1,0,"javascript:window.open(\"https://sites.google.com/site/fjampages/avatars\",\"_blank\",\"width=200,height=600,status=yes,scrollbars=yes,\");void(0)","_self","","Avatars you can use"]);
stm_aix("p8i4","p1i0",[0,"Person To Person File Send","","",-1,-1,0,"https://sites.google.com/site/fjatestsite/home/member-list","_top","","Send a file through thiis app, to someone who is online."]);
stm_aix("p8i5","p1i0",[0,"Mr. C\'s Alternative Hour","","",-1,-1,0,"https://sites.google.com/site/fjatestsite/ashley-cowan-s-alternative-hour","_top","","Ashley Cowan\'s Radio SHow On Croydon Radio (LONDON)"]);
stm_aix("p8i6","p1i0",[0,"F-Jam Group on Facebook","","",-1,-1,0,"https://www.facebook.com/home.php?sk=group_131537443544094&ap=1","_blank","","You can keep track of projects, and discuss with other members via Facebook"]);
stm_aix("p8i7","p1i0",[0,"Useful Links","","",-1,-1,0,"https://sites.google.com/site/fjatestsite/useful-links","_top","","Either related to what we do, or we thought it\'d be interesting to you."]);
stm_ep();
stm_aix("p0i8","p0i3",[0,"News","","",-1,-1,0,"https://sites.google.com/site/fjatestsite/f-jam-news","_top","","Site news"]);
stm_aix("p0i9","p0i1",[0,"Login","","",-1,-1,0,"","_top"]);
stm_bpx("p9","p1",[]);
stm_aix("p9i0","p1i0",[0,"Login to F-Jam Studios","","",-1,-1,0,"https://www.google.com/accounts/ServiceLogin?continue=http%3A%2F%2Fsites.google.com%2F%3Fhl%3Den%26tab%3Dw3&followup=http%3A%2F%2Fsites.google.com%2F%3Fhl%3Den%26tab%3Dw3&hl=en&service=jotspot&passive=true&ul=1","_top","","Login to Google Sites"]);
stm_aix("p9i1","p1i0",[0,"Join F-Jam","","",-1,-1,0,"https://sites.google.com/site/fjatestsite/join-f-jam-studios","_top","","Register"]);
stm_ep();
stm_ep();
stm_sc(1,["transparent","transparent","","",3,3,0,0,"#FFFFF7","#000000","up_disabled.gif","up_enabled.gif",7,9,0,"down_disabled.gif","down_enabled.gif",7,9,0,0,200]);
stm_em();
//-->
</script><br /><center><marquee direction="right" width="63" height="19"><b>&gt;&gt;&gt;&gt;&gt;&gt;</b></marquee>
<b>Hold your cursor over the menu above</b><marquee width="63" height="19"><b>&lt;&lt;&lt;&lt;&lt;&lt;</b></marquee></center>
    ]]>
  </Content>
</Module>